beymax/__init__.py
beymax/args.py
beymax/client.py
beymax/db.py
beymax/suite.py
beymax/ui.py
beymax/utils.py
beymax/control/__init__.py
beymax/control/base.py
beymax/control/dummy.py
beymax/control/webui.py
beymax-1.3.0.dist-info/METADATA
beymax-1.3.0.dist-info/WHEEL
beymax-1.3.0.dist-info/top_level.txt
beymax-1.3.0.dist-info/RECORD
