Metadata-Version: 2.1
Name: beymax
Version: 1.3.0
Summary: A high-level, functional programming wrapper to discord.py
Home-page: https://gitlab.graubert.com/agraubert/beymax
Author: Aaron Graubert
Author-email: aaron@graubert.com
License: MIT
Keywords: discord async asyncio sql sqlalchemy utilities
Classifier: Development Status :: 5 - Production/Stable
Classifier: Framework :: AsyncIO
Classifier: Intended Audience :: Developers
Classifier: License :: OSI Approved :: MIT License
Classifier: Natural Language :: English
Classifier: Operating System :: OS Independent
Classifier: Programming Language :: Python :: 3 :: Only
Classifier: Topic :: Communications :: Chat
Classifier: Topic :: Internet
Classifier: Topic :: Software Development :: Libraries :: Python Modules
Classifier: Topic :: Utilities
Requires-Dist: discord.py==2.1.0
Requires-Dist: aiohttp
Requires-Dist: PyYAML
Requires-Dist: editdistance
Requires-Dist: emoji
Requires-Dist: python-dateutil
Requires-Dist: sqlalchemy<2.0.0,>=1.4.0
Requires-Dist: aiofiles
